DeteksiGempaReal/__init__.py
latestearthquake_indonesia_by_rafiramdhani-0.9.dist-info/LICENSE
latestearthquake_indonesia_by_rafiramdhani-0.9.dist-info/METADATA
latestearthquake_indonesia_by_rafiramdhani-0.9.dist-info/WHEEL
latestearthquake_indonesia_by_rafiramdhani-0.9.dist-info/top_level.txt
latestearthquake_indonesia_by_rafiramdhani-0.9.dist-info/RECORD
